{
  "RecordingType": 1,
  "LevelName": "5e3bd00c-e693-4878-b98e-f375fd89914b",
  "Name": "2019-08-04 20-57-20",
  "MatchName": "2019-08-04 20-52-20",
  "Players": [
    "76561197998646590",
    "76561197998909316",
    "76561197999418456"
  ],
  "Teams": [
    {
      "HasHat": true,
      "HatName": "Dappers",
      "IsCustomHat": false,
      "Players": [
        "76561197999418456"
      ],
      "Score": 6
    },
    {
      "HasHat": true,
      "HatName": "DUCKS",
      "IsCustomHat": false,
      "Players": [
        "76561197998909316"
      ],
      "Score": 4
    },
    {
      "HasHat": true,
      "HatName": "MAJESTY",
      "IsCustomHat": false,
      "Players": [
        "76561197998646590"
      ],
      "Score": 5
    }
  ],
  "TimeEnded": "2019-08-04T20:57:40.5559926+02:00",
  "TimeStarted": "2019-08-04T20:57:20.5034494+02:00",
  "Winner": {
    "HasHat": true,
    "HatName": "Dappers",
    "IsCustomHat": false,
    "Players": [
      "76561197999418456"
    ],
    "Score": 6
  },
  "YoutubeUrl": null,
  "VideoType": 3,
  "VideoStartTime": "00:04:26.5293597",
  "VideoEndTime": "00:04:46.5819029",
  "Tags": []
}