{
  "RecordingType": 1,
  "IsCustomLevel": false,
  "LevelName": "d0d326eb-ee1f-4af9-b2be-b6e4be2bdbfd",
  "Name": "2019-01-02 21-43-12",
  "MatchName": "2019-01-02 21-28-40",
  "Players": [
    "76561197998646590",
    "76561197998909316",
    "76561197999418456",
    "76561197993900183"
  ],
  "Teams": [
    {
      "HasHat": true,
      "HatName": "Player 3",
      "IsCustomHat": true,
      "Players": [
        "76561197999418456"
      ],
      "Score": 4
    },
    {
      "HasHat": true,
      "HatName": "DUCKS",
      "IsCustomHat": false,
      "Players": [
        "76561197998909316"
      ],
      "Score": 10
    },
    {
      "HasHat": true,
      "HatName": "WELDERS",
      "IsCustomHat": false,
      "Players": [
        "76561197993900183"
      ],
      "Score": 7
    },
    {
      "HasHat": true,
      "HatName": "MAJESTY",
      "IsCustomHat": false,
      "Players": [
        "76561197998646590"
      ],
      "Score": 13
    }
  ],
  "TimeEnded": "2019-01-02T21:43:22.0594762+01:00",
  "TimeStarted": "2019-01-02T21:43:12.063064+01:00",
  "Winner": null,
  "YoutubeUrl": null,
  "VideoType": 2,
  "VideoMirrors": [],
  "Tags": []
}