{
  "$id": "24",
  "RecordingType": 1,
  "IsCustomLevel": false,
  "LevelName": "51402a51-f14b-4c7a-8337-11dd72cbad6f",
  "Name": "2018-09-24 18-51-20",
  "MatchName": "2018-09-24 18-36-18",
  "DatabaseIndex": "2018-09-24 18-51-20",
  "Players": [
    {
      "$id": "25",
      "DiscordId": 108174525576777728,
      "Name": "Jvs",
      "NickName": null,
      "UserId": "76561197998646590",
      "DatabaseIndex": "76561197998646590"
    },
    {
      "$id": "26",
      "DiscordId": 105698042438549504,
      "Name": "Willox",
      "NickName": null,
      "UserId": "76561197998909316",
      "DatabaseIndex": "76561197998909316"
    },
    {
      "$id": "27",
      "DiscordId": 167252066773893120,
      "Name": "stevie wonder",
      "NickName": "Raptor",
      "UserId": "76561197993900183",
      "DatabaseIndex": "76561197993900183"
    },
    {
      "$id": "28",
      "DiscordId": 150809682318065664,
      "Name": "Meepen",
      "NickName": null,
      "UserId": "76561198050165746",
      "DatabaseIndex": "76561198050165746"
    }
  ],
  "Teams": [
    {
      "$id": "29",
      "HasHat": true,
      "HatName": "DUCKS",
      "IsCustomHat": false,
      "Players": [
        {
          "$ref": "26"
        }
      ],
      "Score": 11
    },
    {
      "$id": "30",
      "HasHat": true,
      "HatName": "BIG ROBO",
      "IsCustomHat": false,
      "Players": [
        {
          "$ref": "28"
        }
      ],
      "Score": 9
    },
    {
      "$id": "31",
      "HasHat": true,
      "HatName": "TWINTAIL",
      "IsCustomHat": false,
      "Players": [
        {
          "$ref": "27"
        }
      ],
      "Score": 2
    },
    {
      "$id": "32",
      "HasHat": true,
      "HatName": "MAJESTY",
      "IsCustomHat": false,
      "Players": [
        {
          "$ref": "25"
        }
      ],
      "Score": 14
    }
  ],
  "TimeEnded": "2018-09-24T18:51:30.4828632+02:00",
  "TimeStarted": "2018-09-24T18:51:20.8968706+02:00",
  "Winner": {
    "$ref": "32"
  },
  "YoutubeUrl": "fTgMR3gJlqQ",
  "VideoType": 2,
  "VideoMirrors": [],
  "Tags": []
}