{
  "RecordingType": 1,
  "IsCustomLevel": false,
  "LevelName": "036b346a-cc72-4703-996f-b0e623cdb2dc",
  "Name": "2018-07-16 22-28-33",
  "MatchName": "2018-07-16 22-14-12",
  "Players": [
    {
      "DiscordId": 108174525576777728,
      "Name": "Jvs",
      "NickName": null,
      "UserId": "76561197998646590"
    },
    {
      "DiscordId": 94866365525008384,
      "Name": "metaMan",
      "NickName": null,
      "UserId": "76561197999418456"
    },
    {
      "DiscordId": 150809682318065664,
      "Name": "Meepen",
      "NickName": null,
      "UserId": "76561198050165746"
    },
    {
      "DiscordId": 105698042438549504,
      "Name": "Willox",
      "NickName": null,
      "UserId": "76561197998909316"
    }
  ],
  "Teams": [
    {
      "HasHat": true,
      "HatName": "MAJESTY",
      "IsCustomHat": false,
      "Players": [
        {
          "DiscordId": 108174525576777728,
          "Name": "Jvs",
          "NickName": null,
          "UserId": "76561197998646590"
        }
      ],
      "Score": 17
    },
    {
      "HasHat": true,
      "HatName": "Player 2",
      "IsCustomHat": true,
      "Players": [
        {
          "DiscordId": 94866365525008384,
          "Name": "metaMan",
          "NickName": null,
          "UserId": "76561197999418456"
        }
      ],
      "Score": 7
    },
    {
      "HasHat": true,
      "HatName": "PONYCAP",
      "IsCustomHat": false,
      "Players": [
        {
          "DiscordId": 150809682318065664,
          "Name": "Meepen",
          "NickName": null,
          "UserId": "76561198050165746"
        }
      ],
      "Score": 5
    },
    {
      "HasHat": true,
      "HatName": "DUCKS",
      "IsCustomHat": false,
      "Players": [
        {
          "DiscordId": 105698042438549504,
          "Name": "Willox",
          "NickName": null,
          "UserId": "76561197998909316"
        }
      ],
      "Score": 4
    }
  ],
  "TimeEnded": "2018-07-16T22:28:50.5753901+02:00",
  "TimeStarted": "2018-07-16T22:28:33.9818354+02:00",
  "Winner": {
    "HasHat": true,
    "HatName": "DUCKS",
    "IsCustomHat": false,
    "Players": [
      {
        "DiscordId": 105698042438549504,
        "Name": "Willox",
        "NickName": null,
        "UserId": "76561197998909316"
      }
    ],
    "Score": 4
  },
  "YoutubeUrl": "zPXZN2S0aek",
  "VideoType": 2,
  "VideoMirrors": [
    {
      "MirrorType": 1,
      "URL": "https://cdn.discordapp.com/attachments/570296205272285216/572683480849317918/2018-07-16_22-28-33.mp4"
    }
  ],
  "Tags": []
}