{
  "RecordingType": 1,
  "IsCustomLevel": false,
  "LevelName": "c63c670e-d37e-430a-8342-55f3d7f4cd26",
  "Name": "2018-07-13 23-14-04",
  "MatchName": "2018-07-13 23-12-24",
  "Players": [
    {
      "DiscordId": 108174525576777728,
      "Name": "Jvs",
      "NickName": null,
      "UserId": "76561197998646590"
    },
    {
      "DiscordId": 94866365525008384,
      "Name": "metaMan",
      "NickName": null,
      "UserId": "76561197999418456"
    },
    {
      "DiscordId": 105698042438549504,
      "Name": "Willox",
      "NickName": null,
      "UserId": "76561197998909316"
    }
  ],
  "Teams": [
    {
      "HasHat": true,
      "HatName": "MAJESTY",
      "IsCustomHat": false,
      "Players": [
        {
          "DiscordId": 108174525576777728,
          "Name": "Jvs",
          "NickName": null,
          "UserId": "76561197998646590"
        }
      ],
      "Score": 2
    },
    {
      "HasHat": true,
      "HatName": "Player 2",
      "IsCustomHat": true,
      "Players": [
        {
          "DiscordId": 94866365525008384,
          "Name": "metaMan",
          "NickName": null,
          "UserId": "76561197999418456"
        }
      ],
      "Score": 2
    },
    {
      "HasHat": true,
      "HatName": "DUCKS",
      "IsCustomHat": false,
      "Players": [
        {
          "DiscordId": 105698042438549504,
          "Name": "Willox",
          "NickName": null,
          "UserId": "76561197998909316"
        }
      ],
      "Score": 2
    }
  ],
  "TimeEnded": "2018-07-13T23:14:20.3069346+02:00",
  "TimeStarted": "2018-07-13T23:14:04.422591+02:00",
  "Winner": {
    "HasHat": true,
    "HatName": "MAJESTY",
    "IsCustomHat": false,
    "Players": [
      {
        "DiscordId": 108174525576777728,
        "Name": "Jvs",
        "NickName": null,
        "UserId": "76561197998646590"
      }
    ],
    "Score": 2
  },
  "YoutubeUrl": "ShNqdqQW7Zo",
  "VideoType": 2,
  "VideoMirrors": [
    {
      "MirrorType": 1,
      "URL": "https://cdn.discordapp.com/attachments/570296205272285216/572501065115631626/2018-07-13_23-14-04.mp4"
    }
  ],
  "Tags": []
}