{
  "RecordingType": 1,
  "LevelName": "1a123d6a-96a9-4c9e-8207-e6cd58d782dd",
  "Name": "2019-11-17 21-11-04",
  "MatchName": "2019-11-17 21-06-07",
  "Players": [
    "76561197998646590",
    "76561197998909316",
    "76561198050165746"
  ],
  "Teams": [
    {
      "HasHat": true,
      "HatName": "DUCKS",
      "IsCustomHat": false,
      "Players": [
        "76561197998909316"
      ],
      "Score": 5
    },
    {
      "HasHat": true,
      "HatName": "Witchtime",
      "IsCustomHat": false,
      "Players": [
        "76561198050165746"
      ],
      "Score": 2
    },
    {
      "HasHat": true,
      "HatName": "MAJESTY",
      "IsCustomHat": false,
      "Players": [
        "76561197998646590"
      ],
      "Score": 6
    }
  ],
  "TimeEnded": "2019-11-17T21:11:22.0275879+01:00",
  "TimeStarted": "2019-11-17T21:11:04.2021639+01:00",
  "Winner": {
    "HasHat": true,
    "HatName": "DUCKS",
    "IsCustomHat": false,
    "Players": [
      "76561197998909316"
    ],
    "Score": 5
  },
  "YoutubeUrl": null,
  "VideoType": 2,
  "VideoMirrors": [],
  "Tags": []
}