{
  "$id": "434",
  "RecordingType": 1,
  "IsCustomLevel": false,
  "LevelName": "da443459-9393-482b-9193-cfbe073dd515",
  "Name": "2018-09-24 18-32-41",
  "MatchName": "2018-09-24 18-23-05",
  "DatabaseIndex": "2018-09-24 18-32-41",
  "Players": [
    {
      "$id": "435",
      "DiscordId": 108174525576777728,
      "Name": "Jvs",
      "NickName": null,
      "UserId": "76561197998646590",
      "DatabaseIndex": "76561197998646590"
    },
    {
      "$id": "436",
      "DiscordId": 105698042438549504,
      "Name": "Willox",
      "NickName": null,
      "UserId": "76561197998909316",
      "DatabaseIndex": "76561197998909316"
    },
    {
      "$id": "437",
      "DiscordId": 167252066773893120,
      "Name": "stevie wonder",
      "NickName": "Raptor",
      "UserId": "76561197993900183",
      "DatabaseIndex": "76561197993900183"
    },
    {
      "$id": "438",
      "DiscordId": 150809682318065664,
      "Name": "Meepen",
      "NickName": null,
      "UserId": "76561198050165746",
      "DatabaseIndex": "76561198050165746"
    }
  ],
  "Teams": [
    {
      "$id": "439",
      "HasHat": true,
      "HatName": "DUCKS",
      "IsCustomHat": false,
      "Players": [
        {
          "$ref": "436"
        }
      ],
      "Score": 2
    },
    {
      "$id": "440",
      "HasHat": true,
      "HatName": "BIG ROBO",
      "IsCustomHat": false,
      "Players": [
        {
          "$ref": "438"
        }
      ],
      "Score": 6
    },
    {
      "$id": "441",
      "HasHat": true,
      "HatName": "TWINTAIL",
      "IsCustomHat": false,
      "Players": [
        {
          "$ref": "437"
        }
      ],
      "Score": 4
    },
    {
      "$id": "442",
      "HasHat": true,
      "HatName": "MAJESTY",
      "IsCustomHat": false,
      "Players": [
        {
          "$ref": "435"
        }
      ],
      "Score": 12
    }
  ],
  "TimeEnded": "2018-09-24T18:33:16.959503+02:00",
  "TimeStarted": "2018-09-24T18:32:41.6088994+02:00",
  "Winner": {
    "$ref": "439"
  },
  "YoutubeUrl": "ez2EfPrqtt4",
  "VideoType": 2,
  "VideoMirrors": [],
  "Tags": []
}