{
  "RecordingType": 1,
  "IsCustomLevel": false,
  "LevelName": "cdc37645-debf-4184-bc2c-9ad6e9026088",
  "Name": "2018-08-15 22-36-13",
  "MatchName": "2018-08-15 22-28-34",
  "Players": [
    {
      "DiscordId": 108174525576777728,
      "Name": "Jvs",
      "NickName": null,
      "UserId": "76561197998646590"
    },
    {
      "DiscordId": 150809682318065664,
      "Name": "Meepen",
      "NickName": null,
      "UserId": "76561198050165746"
    },
    {
      "DiscordId": 105698042438549504,
      "Name": "Willox",
      "NickName": null,
      "UserId": "76561197998909316"
    }
  ],
  "Teams": [
    {
      "HasHat": true,
      "HatName": "DUCKS",
      "IsCustomHat": false,
      "Players": [
        {
          "DiscordId": 105698042438549504,
          "Name": "Willox",
          "NickName": null,
          "UserId": "76561197998909316"
        }
      ],
      "Score": 5
    },
    {
      "HasHat": true,
      "HatName": "PONYCAP",
      "IsCustomHat": false,
      "Players": [
        {
          "DiscordId": 150809682318065664,
          "Name": "Meepen",
          "NickName": null,
          "UserId": "76561198050165746"
        }
      ],
      "Score": 4
    },
    {
      "HasHat": true,
      "HatName": "MAJESTY",
      "IsCustomHat": false,
      "Players": [
        {
          "DiscordId": 108174525576777728,
          "Name": "Jvs",
          "NickName": null,
          "UserId": "76561197998646590"
        }
      ],
      "Score": 12
    }
  ],
  "TimeEnded": "2018-08-15T22:36:25.4416119+02:00",
  "TimeStarted": "2018-08-15T22:36:13.8549838+02:00",
  "Winner": {
    "HasHat": true,
    "HatName": "MAJESTY",
    "IsCustomHat": false,
    "Players": [
      {
        "DiscordId": 108174525576777728,
        "Name": "Jvs",
        "NickName": null,
        "UserId": "76561197998646590"
      }
    ],
    "Score": 12
  },
  "YoutubeUrl": "oHmWsgUAPbE",
  "VideoType": 2,
  "VideoMirrors": [
    {
      "MirrorType": 1,
      "URL": "https://cdn.discordapp.com/attachments/570296205272285216/572725085878747141/2018-08-15_22-36-13.mp4"
    }
  ],
  "Tags": []
}