{
  "RecordingType": 1,
  "IsCustomLevel": false,
  "LevelName": "cdc37645-debf-4184-bc2c-9ad6e9026088",
  "Name": "2019-01-05 21-25-42",
  "MatchName": "2019-01-05 21-21-32",
  "Players": [
    "76561197998646590",
    "76561197998909316",
    "76561197999418456"
  ],
  "Teams": [
    {
      "HasHat": true,
      "HatName": "Player 3",
      "IsCustomHat": true,
      "Players": [
        "76561197999418456"
      ],
      "Score": 7
    },
    {
      "HasHat": true,
      "HatName": "DUCKS",
      "IsCustomHat": false,
      "Players": [
        "76561197998909316"
      ],
      "Score": 4
    },
    {
      "HasHat": true,
      "HatName": "MAJESTY",
      "IsCustomHat": false,
      "Players": [
        "76561197998646590"
      ],
      "Score": 5
    }
  ],
  "TimeEnded": "2019-01-05T21:25:51.8746301+01:00",
  "TimeStarted": "2019-01-05T21:25:42.5347621+01:00",
  "Winner": {
    "HasHat": true,
    "HatName": "MAJESTY",
    "IsCustomHat": false,
    "Players": [
      "76561197998646590"
    ],
    "Score": 5
  },
  "YoutubeUrl": null,
  "VideoType": 2,
  "VideoMirrors": [],
  "Tags": []
}