{
  "$id": "1",
  "RecordingType": 1,
  "IsCustomLevel": false,
  "LevelName": "b7706cd6-64e9-4efb-9818-d57976c145cd",
  "Name": "2018-09-17 21-53-55",
  "MatchName": "2018-09-17 21-48-40",
  "Players": [
    {
      "$id": "2",
      "DiscordId": 108174525576777728,
      "Name": "Jvs",
      "NickName": null,
      "UserId": "76561197998646590"
    },
    {
      "$id": "3",
      "DiscordId": 105698042438549504,
      "Name": "Willox",
      "NickName": null,
      "UserId": "76561197998909316"
    },
    {
      "$id": "4",
      "DiscordId": 150809682318065664,
      "Name": "Meepen",
      "NickName": null,
      "UserId": "76561198050165746"
    },
    {
      "$id": "5",
      "DiscordId": 94866365525008384,
      "Name": "MetaMan",
      "NickName": null,
      "UserId": "76561197999418456"
    }
  ],
  "Teams": [
    {
      "$id": "6",
      "HasHat": true,
      "HatName": "Player 4",
      "IsCustomHat": true,
      "Players": [
        {
          "$ref": "5"
        }
      ],
      "Score": 4
    },
    {
      "$id": "7",
      "HasHat": true,
      "HatName": "DUCKS",
      "IsCustomHat": false,
      "Players": [
        {
          "$ref": "3"
        }
      ],
      "Score": 3
    },
    {
      "$id": "8",
      "HasHat": true,
      "HatName": "PONYCAP",
      "IsCustomHat": false,
      "Players": [
        {
          "$ref": "4"
        }
      ],
      "Score": 2
    },
    {
      "$id": "9",
      "HasHat": true,
      "HatName": "MAJESTY",
      "IsCustomHat": false,
      "Players": [
        {
          "$ref": "2"
        }
      ],
      "Score": 6
    }
  ],
  "TimeEnded": "2018-09-17T21:54:29.3041791+02:00",
  "TimeStarted": "2018-09-17T21:53:55.858545+02:00",
  "Winner": {
    "$ref": "9"
  },
  "YoutubeUrl": "4dmMVz0ZotM",
  "VideoType": 2,
  "VideoMirrors": []
}