{
  "RecordingType": 1,
  "LevelName": "23768577-4b34-4de9-9ce7-512d67dabbf0",
  "Name": "2019-06-21 22-11-09",
  "MatchName": "2019-06-21 22-04-23",
  "Players": [
    "76561197998646590",
    "76561197999418456"
  ],
  "Teams": [
    {
      "HasHat": true,
      "HatName": "Agents",
      "IsCustomHat": false,
      "Players": [
        "76561197999418456"
      ],
      "Score": 8
    },
    {
      "HasHat": true,
      "HatName": "MAJESTY",
      "IsCustomHat": false,
      "Players": [
        "76561197998646590"
      ],
      "Score": 12
    }
  ],
  "TimeEnded": "2019-06-21T22:11:17.8183121+02:00",
  "TimeStarted": "2019-06-21T22:11:09.4484098+02:00",
  "Winner": {
    "HasHat": true,
    "HatName": "MAJESTY",
    "IsCustomHat": false,
    "Players": [
      "76561197998646590"
    ],
    "Score": 12
  },
  "YoutubeUrl": null,
  "VideoType": 3,
  "VideoStartTime": "00:05:45.8934941",
  "VideoEndTime": "00:05:54.2633964",
  "Tags": []
}