{
  "RecordingType": 1,
  "IsCustomLevel": false,
  "LevelName": "036a2542-89b2-4d44-a5e0-a927400ccbd2",
  "Name": "2018-09-12 22-46-38",
  "MatchName": "2018-09-12 22-30-58",
  "Players": [
    "76561197998646590",
    "76561197998909316",
    "76561198021148954"
  ],
  "Teams": [
    {
      "HasHat": true,
      "HatName": "DUCKS",
      "IsCustomHat": false,
      "Players": [
        "76561197998909316"
      ],
      "Score": 12
    },
    {
      "HasHat": true,
      "HatName": "Chancy",
      "IsCustomHat": false,
      "Players": [
        "76561198021148954"
      ],
      "Score": 14
    },
    {
      "HasHat": true,
      "HatName": "MAJESTY",
      "IsCustomHat": false,
      "Players": [
        "76561197998646590"
      ],
      "Score": 19
    }
  ],
  "TimeEnded": "2018-09-12T22:46:47.9955534+02:00",
  "TimeStarted": "2018-09-12T22:46:38.7552048+02:00",
  "Winner": {
    "HasHat": true,
    "HatName": "MAJESTY",
    "IsCustomHat": false,
    "Players": [
      "76561197998646590"
    ],
    "Score": 19
  },
  "YoutubeUrl": "UZP7qmaMces",
  "VideoType": 2,
  "VideoMirrors": [
    {
      "MirrorType": 1,
      "URL": "https://cdn.discordapp.com/attachments/570296205272285216/572744067063087104/2018-09-12_22-46-38.mp4"
    }
  ],
  "Tags": []
}