{
  "$id": "1",
  "RecordingType": 1,
  "IsCustomLevel": false,
  "LevelName": "2aa226a3-7db9-436b-adff-bbcf01f8d4a1",
  "Name": "2018-07-24 22-58-53",
  "MatchName": "2018-07-24 22-47-41",
  "Players": [
    {
      "$id": "2",
      "DiscordId": 108174525576777728,
      "Name": "Jvs",
      "NickName": null,
      "UserId": "76561197998646590"
    },
    {
      "$id": "3",
      "DiscordId": 105698042438549504,
      "Name": "Willox",
      "NickName": null,
      "UserId": "76561197998909316"
    },
    {
      "$id": "4",
      "DiscordId": 94866365525008384,
      "Name": "metaMan",
      "NickName": null,
      "UserId": "76561197999418456"
    }
  ],
  "Teams": [
    {
      "$id": "5",
      "hasHat": true,
      "hatName": "MAJESTY",
      "isCustomHat": false,
      "Players": [
        {
          "$ref": "2"
        }
      ],
      "score": 10
    },
    {
      "$id": "6",
      "hasHat": true,
      "hatName": "DUCKS",
      "isCustomHat": false,
      "Players": [
        {
          "$ref": "3"
        }
      ],
      "score": 8
    },
    {
      "$id": "7",
      "hasHat": true,
      "hatName": "Player 3",
      "isCustomHat": true,
      "Players": [
        {
          "$ref": "4"
        }
      ],
      "score": 5
    }
  ],
  "TimeEnded": "2018-07-24T20:59:09.7056013+00:00",
  "TimeStarted": "2018-07-24T20:58:53.7195125+00:00",
  "Winner": {
    "$ref": "5"
  },
  "YoutubeUrl": "ykDACUxV0Ns",
  "VideoType": 2,
  "VideoMirrors": [
    {
      "$id": "8",
      "MirrorType": 1,
      "URL": "https://cdn.discordapp.com/attachments/570296205272285216/572690011770847237/2018-07-24_22-58-53.mp4"
    }
  ]
}