{
  "RecordingType": 1,
  "IsCustomLevel": false,
  "LevelName": "a52f00a9-5e9f-49af-bf9c-e4eabc14f490",
  "Name": "2018-09-04 21-54-27",
  "MatchName": "2018-09-04 21-43-28",
  "Players": [
    "76561197998646590",
    "76561198050165746",
    "76561197999418456",
    "76561197998909316"
  ],
  "Teams": [
    {
      "HasHat": true,
      "HatName": "Player 3",
      "IsCustomHat": true,
      "Players": [
        "76561197999418456"
      ],
      "Score": 6
    },
    {
      "HasHat": true,
      "HatName": "DUCKS",
      "IsCustomHat": false,
      "Players": [
        "76561197998909316"
      ],
      "Score": 9
    },
    {
      "HasHat": true,
      "HatName": "Hearts",
      "IsCustomHat": false,
      "Players": [
        "76561198050165746"
      ],
      "Score": 1
    },
    {
      "HasHat": true,
      "HatName": "MAJESTY",
      "IsCustomHat": false,
      "Players": [
        "76561197998646590"
      ],
      "Score": 10
    }
  ],
  "TimeEnded": "2018-09-04T21:54:58.5168691+02:00",
  "TimeStarted": "2018-09-04T21:54:27.3536226+02:00",
  "Winner": {
    "HasHat": true,
    "HatName": "Player 3",
    "IsCustomHat": true,
    "Players": [
      "76561197999418456"
    ],
    "Score": 6
  },
  "YoutubeUrl": "SxwGxm2JNMs",
  "VideoType": 2,
  "VideoMirrors": [
    {
      "MirrorType": 1,
      "URL": "https://cdn.discordapp.com/attachments/570296205272285216/572737469007790135/2018-09-04_21-54-27.mp4"
    }
  ],
  "Tags": []
}