{
  "RecordingType": 1,
  "LevelName": "23ec9c56-dbcc-4384-9507-5b0f80cb0111",
  "Name": "2018-12-23 21-47-30",
  "MatchName": "2018-12-23 21-46-13",
  "Players": [
    "76561197998646590",
    "76561198050165746",
    "76561197998909316"
  ],
  "Teams": [
    {
      "HasHat": true,
      "HatName": "DUCKS",
      "IsCustomHat": false,
      "Players": [
        "76561197998909316"
      ],
      "Score": 3
    },
    {
      "HasHat": true,
      "HatName": "PONYCAP",
      "IsCustomHat": false,
      "Players": [
        "76561198050165746"
      ],
      "Score": 1
    },
    {
      "HasHat": true,
      "HatName": "MAJESTY",
      "IsCustomHat": false,
      "Players": [
        "76561197998646590"
      ],
      "Score": 0
    }
  ],
  "TimeEnded": "2018-12-23T21:47:47.1858545+01:00",
  "TimeStarted": "2018-12-23T21:47:30.280139+01:00",
  "Winner": {
    "HasHat": true,
    "HatName": "DUCKS",
    "IsCustomHat": false,
    "Players": [
      "76561197998909316"
    ],
    "Score": 3
  },
  "YoutubeUrl": null,
  "VideoType": 3,
  "VideoStartTime": "00:01:09.0980681",
  "VideoEndTime": "00:01:26.0037836",
  "Tags": []
}