{
  "RecordingType": 1,
  "IsCustomLevel": false,
  "LevelName": "fe6c9c0e-eb83-4588-84ff-9ecc7f46b4b5",
  "Name": "2018-06-08 21-08-29",
  "MatchName": "2018-06-08 20-56-06",
  "Players": [
    "76561197998909316",
    "76561197998646590",
    "76561198050165746",
    "76561197999418456"
  ],
  "Teams": [
    {
      "HasHat": true,
      "HatName": "DUCKS",
      "IsCustomHat": false,
      "Players": [
        "76561197998909316"
      ],
      "Score": 2
    },
    {
      "HasHat": true,
      "HatName": "MOONWALK",
      "IsCustomHat": false,
      "Players": [
        "76561197998646590"
      ],
      "Score": 10
    },
    {
      "HasHat": true,
      "HatName": "Agents",
      "IsCustomHat": false,
      "Players": [
        "76561198050165746"
      ],
      "Score": 7
    },
    {
      "HasHat": true,
      "HatName": "Sombreros",
      "IsCustomHat": false,
      "Players": [
        "76561197999418456"
      ],
      "Score": 10
    }
  ],
  "TimeEnded": "2018-06-08T21:08:45.5839367+02:00",
  "TimeStarted": "2018-06-08T21:08:29.4511398+02:00",
  "Winner": {
    "HasHat": true,
    "HatName": "MOONWALK",
    "IsCustomHat": false,
    "Players": [
      "76561197998646590"
    ],
    "Score": 10
  },
  "YoutubeUrl": "q5jTG-SZmBM",
  "VideoType": 2,
  "VideoMirrors": [
    {
      "MirrorType": 1,
      "URL": "https://cdn.discordapp.com/attachments/570296205272285216/572468987045347340/2018-06-08_21-08-29.mp4"
    }
  ],
  "Tags": []
}