{
  "$id": "681",
  "RecordingType": 1,
  "IsCustomLevel": true,
  "LevelName": "d2d57e18-5856-4102-88ec-56406a4eea0d",
  "Name": "2019-06-15 20-17-22",
  "MatchName": "2019-06-15 20-07-19",
  "DatabaseIndex": "2019-06-15 20-17-22",
  "Players": [
    {
      "$id": "682",
      "DiscordId": 108174525576777728,
      "Name": "Jvs",
      "NickName": null,
      "UserId": "76561197998646590",
      "DatabaseIndex": "76561197998646590"
    },
    {
      "$id": "683",
      "DiscordId": 105698042438549504,
      "Name": "Willox",
      "NickName": null,
      "UserId": "76561197998909316",
      "DatabaseIndex": "76561197998909316"
    },
    {
      "$id": "684",
      "DiscordId": 94866365525008384,
      "Name": "MetaMan",
      "NickName": null,
      "UserId": "76561197999418456",
      "DatabaseIndex": "76561197999418456"
    }
  ],
  "Teams": [
    {
      "$id": "685",
      "HasHat": true,
      "HatName": "DUCKS",
      "IsCustomHat": false,
      "Players": [
        {
          "$id": "686",
          "DiscordId": 105698042438549504,
          "Name": "Willox",
          "NickName": null,
          "UserId": "76561197998909316",
          "DatabaseIndex": "76561197998909316"
        }
      ],
      "Score": 13
    },
    {
      "$id": "687",
      "HasHat": true,
      "HatName": "MAJESTY",
      "IsCustomHat": false,
      "Players": [
        {
          "$id": "688",
          "DiscordId": 108174525576777728,
          "Name": "Jvs",
          "NickName": null,
          "UserId": "76561197998646590",
          "DatabaseIndex": "76561197998646590"
        }
      ],
      "Score": 10
    },
    {
      "$id": "689",
      "HasHat": true,
      "HatName": "MOONWALK",
      "IsCustomHat": false,
      "Players": [
        {
          "$id": "690",
          "DiscordId": 94866365525008384,
          "Name": "MetaMan",
          "NickName": null,
          "UserId": "76561197999418456",
          "DatabaseIndex": "76561197999418456"
        }
      ],
      "Score": 9
    }
  ],
  "TimeEnded": "2019-06-15T20:17:31.5393735+02:00",
  "TimeStarted": "2019-06-15T20:17:22.2245045+02:00",
  "Winner": {
    "$ref": "689"
  },
  "YoutubeUrl": null,
  "VideoType": 2,
  "VideoMirrors": [],
  "Tags": []
}