{
  "$id": "241",
  "RecordingType": 1,
  "IsCustomLevel": true,
  "LevelName": "7d4d8017-c553-4e90-870c-1f7e38b83ea8",
  "Name": "2019-06-13 21-58-42",
  "MatchName": "2019-06-13 21-55-31",
  "DatabaseIndex": "2019-06-13 21-58-42",
  "Players": [
    {
      "$id": "242",
      "DiscordId": 108174525576777728,
      "Name": "Jvs",
      "NickName": null,
      "UserId": "76561197998646590",
      "DatabaseIndex": "76561197998646590"
    },
    {
      "$id": "243",
      "DiscordId": 105698042438549504,
      "Name": "Willox",
      "NickName": null,
      "UserId": "76561197998909316",
      "DatabaseIndex": "76561197998909316"
    },
    {
      "$id": "244",
      "DiscordId": 94866365525008384,
      "Name": "MetaMan",
      "NickName": null,
      "UserId": "76561197999418456",
      "DatabaseIndex": "76561197999418456"
    }
  ],
  "Teams": [
    {
      "$id": "245",
      "HasHat": true,
      "HatName": "DUCKS",
      "IsCustomHat": false,
      "Players": [
        {
          "$id": "246",
          "DiscordId": 105698042438549504,
          "Name": "Willox",
          "NickName": null,
          "UserId": "76561197998909316",
          "DatabaseIndex": "76561197998909316"
        }
      ],
      "Score": 5
    },
    {
      "$id": "247",
      "HasHat": true,
      "HatName": "MAJESTY",
      "IsCustomHat": false,
      "Players": [
        {
          "$id": "248",
          "DiscordId": 108174525576777728,
          "Name": "Jvs",
          "NickName": null,
          "UserId": "76561197998646590",
          "DatabaseIndex": "76561197998646590"
        }
      ],
      "Score": 5
    },
    {
      "$id": "249",
      "HasHat": true,
      "HatName": "MOONWALK",
      "IsCustomHat": false,
      "Players": [
        {
          "$id": "250",
          "DiscordId": 94866365525008384,
          "Name": "MetaMan",
          "NickName": null,
          "UserId": "76561197999418456",
          "DatabaseIndex": "76561197999418456"
        }
      ],
      "Score": 1
    }
  ],
  "TimeEnded": "2019-06-13T21:59:01.2912868+02:00",
  "TimeStarted": "2019-06-13T21:58:42.7926068+02:00",
  "Winner": {
    "$ref": "245"
  },
  "YoutubeUrl": null,
  "VideoType": 2,
  "VideoMirrors": [],
  "Tags": []
}