{
  "RecordingType": 1,
  "IsCustomLevel": false,
  "LevelName": "57047338-2ce8-424f-bdf6-ce3804b7f7fc",
  "Name": "2018-09-16 22-26-40",
  "MatchName": "2018-09-16 22-16-34",
  "Players": [
    "76561197998646590",
    "76561197993900183",
    "76561197999418456",
    "76561197998909316"
  ],
  "Teams": [
    {
      "HasHat": true,
      "HatName": "Player 3",
      "IsCustomHat": true,
      "Players": [
        "76561197999418456"
      ],
      "Score": 10
    },
    {
      "HasHat": true,
      "HatName": "DUCKS",
      "IsCustomHat": false,
      "Players": [
        "76561197998909316"
      ],
      "Score": 8
    },
    {
      "HasHat": true,
      "HatName": "Wizards",
      "IsCustomHat": false,
      "Players": [
        "76561197993900183"
      ],
      "Score": 1
    },
    {
      "HasHat": true,
      "HatName": "MAJESTY",
      "IsCustomHat": false,
      "Players": [
        "76561197998646590"
      ],
      "Score": 4
    }
  ],
  "TimeEnded": "2018-09-16T22:26:55.1627935+02:00",
  "TimeStarted": "2018-09-16T22:26:40.9414955+02:00",
  "Winner": {
    "HasHat": true,
    "HatName": "DUCKS",
    "IsCustomHat": false,
    "Players": [
      "76561197998909316"
    ],
    "Score": 8
  },
  "YoutubeUrl": "Nj6XG_PPZ1k",
  "VideoType": 2,
  "VideoMirrors": [
    {
      "MirrorType": 1,
      "URL": "https://cdn.discordapp.com/attachments/570296205272285216/572750346972299265/2018-09-16_22-26-40.mp4"
    }
  ],
  "Tags": []
}