{
  "RecordingType": 1,
  "IsCustomLevel": false,
  "LevelName": "51402a51-f14b-4c7a-8337-11dd72cbad6f",
  "Name": "2018-09-14 23-09-30",
  "MatchName": "2018-09-14 23-02-32",
  "Players": [
    "76561197998646590",
    "76561197998909316",
    "76561198050165746"
  ],
  "Teams": [
    {
      "HasHat": true,
      "HatName": "DUCKS",
      "IsCustomHat": false,
      "Players": [
        "76561197998909316"
      ],
      "Score": 5
    },
    {
      "HasHat": true,
      "HatName": "Agents",
      "IsCustomHat": false,
      "Players": [
        "76561198050165746"
      ],
      "Score": 4
    },
    {
      "HasHat": true,
      "HatName": "MAJESTY",
      "IsCustomHat": false,
      "Players": [
        "76561197998646590"
      ],
      "Score": 11
    }
  ],
  "TimeEnded": "2018-09-14T23:09:42.0375338+02:00",
  "TimeStarted": "2018-09-14T23:09:30.1859504+02:00",
  "Winner": {
    "HasHat": true,
    "HatName": "DUCKS",
    "IsCustomHat": false,
    "Players": [
      "76561197998909316"
    ],
    "Score": 5
  },
  "YoutubeUrl": "Xnpqs2ioYWM",
  "VideoType": 2,
  "VideoMirrors": [
    {
      "MirrorType": 1,
      "URL": "https://cdn.discordapp.com/attachments/570296205272285216/572746561587773452/2018-09-14_23-09-30.mp4"
    }
  ],
  "Tags": []
}