{
  "RecordingType": 1,
  "IsCustomLevel": false,
  "LevelName": "7a6568bc-1589-44a7-8683-cb123cfd9cd3",
  "Name": "2019-05-21 21-59-16",
  "MatchName": "2019-05-21 21-50-42",
  "Players": [
    "76561197998646590",
    "76561197998909316",
    "76561197999418456"
  ],
  "Teams": [
    {
      "HasHat": true,
      "HatName": "Sombreros",
      "IsCustomHat": false,
      "Players": [
        "76561197999418456"
      ],
      "Score": 6
    },
    {
      "HasHat": true,
      "HatName": "DUCKS",
      "IsCustomHat": false,
      "Players": [
        "76561197998909316"
      ],
      "Score": 6
    },
    {
      "HasHat": true,
      "HatName": "MAJESTY",
      "IsCustomHat": false,
      "Players": [
        "76561197998646590"
      ],
      "Score": 12
    }
  ],
  "TimeEnded": "2019-05-21T21:59:35.8983956+02:00",
  "TimeStarted": "2019-05-21T21:59:16.5806554+02:00",
  "Winner": {
    "HasHat": true,
    "HatName": "MAJESTY",
    "IsCustomHat": false,
    "Players": [
      "76561197998646590"
    ],
    "Score": 12
  },
  "YoutubeUrl": null,
  "VideoType": 2,
  "VideoMirrors": [],
  "Tags": []
}