{
  "Name": "2018-06-05 21-18-48",
  "Players": [
    {
      "DiscordId": 105698042438549504,
      "Name": "Willox",
      "NickName": null,
      "UserId": "76561197998909316"
    },
    {
      "DiscordId": 150809682318065664,
      "Name": "Meepen",
      "NickName": null,
      "UserId": "76561198050165746"
    },
    {
      "DiscordId": 108174525576777728,
      "Name": "Jvs",
      "NickName": null,
      "UserId": "76561197998646590"
    }
  ],
  "Rounds": [
    "2018-06-05 21-18-48",
    "2018-06-05 21-19-09",
    "2018-06-05 21-19-23",
    "2018-06-05 21-19-36",
    "2018-06-05 21-20-06",
    "2018-06-05 21-20-26",
    "2018-06-05 21-20-57",
    "2018-06-05 21-21-13",
    "2018-06-05 21-21-32",
    "2018-06-05 21-21-48",
    "2018-06-05 21-22-33",
    "2018-06-05 21-23-00",
    "2018-06-05 21-23-19",
    "2018-06-05 21-23-36",
    "2018-06-05 21-23-54",
    "2018-06-05 21-24-20",
    "2018-06-05 21-24-28",
    "2018-06-05 21-24-58",
    "2018-06-05 21-25-13",
    "2018-06-05 21-25-30",
    "2018-06-05 21-25-50",
    "2018-06-05 21-26-08",
    "2018-06-05 21-26-15",
    "2018-06-05 21-26-30",
    "2018-06-05 21-26-40",
    "2018-06-05 21-27-11",
    "2018-06-05 21-27-28",
    "2018-06-05 21-27-42",
    "2018-06-05 21-28-10",
    "2018-06-05 21-28-32"
  ],
  "Teams": [
    {
      "HasHat": true,
      "HatName": "DUCKS",
      "IsCustomHat": false,
      "Players": [
        {
          "DiscordId": 105698042438549504,
          "Name": "Willox",
          "NickName": null,
          "UserId": "76561197998909316"
        }
      ],
      "Score": 4
    },
    {
      "HasHat": true,
      "HatName": "brad",
      "IsCustomHat": false,
      "Players": [
        {
          "DiscordId": 150809682318065664,
          "Name": "Meepen",
          "NickName": null,
          "UserId": "76561198050165746"
        }
      ],
      "Score": 5
    },
    {
      "HasHat": true,
      "HatName": "MOONWALK",
      "IsCustomHat": false,
      "Players": [
        {
          "DiscordId": 108174525576777728,
          "Name": "Jvs",
          "NickName": null,
          "UserId": "76561197998646590"
        }
      ],
      "Score": 17
    }
  ],
  "TimeEnded": "2018-06-05T21:29:06.3467897+02:00",
  "TimeStarted": "2018-06-05T21:18:48.1321817+02:00",
  "Winner": {
    "HasHat": true,
    "HatName": "MOONWALK",
    "IsCustomHat": false,
    "Players": [
      {
        "DiscordId": 108174525576777728,
        "Name": "Jvs",
        "NickName": null,
        "UserId": "76561197998646590"
      }
    ],
    "Score": 17
  },
  "YoutubeUrl": "PL13R2KKE1DTv-DotJoAwLWqr2S9qyqGcC",
  "VideoType": 1,
  "VideoMirrors": [],
  "Tags": []
}