{
  "RecordingType": 1,
  "LevelName": "eaf60e63-d8bd-4396-b6c8-bf638a408322",
  "Name": "2019-07-27 21-51-22",
  "MatchName": "2019-07-27 21-40-36",
  "Players": [
    "76561197998646590",
    "76561197999418456",
    "76561197998909316"
  ],
  "Teams": [
    {
      "HasHat": true,
      "HatName": "DUCKS",
      "IsCustomHat": false,
      "Players": [
        "76561197998909316"
      ],
      "Score": 9
    },
    {
      "HasHat": true,
      "HatName": "Cyborgs",
      "IsCustomHat": false,
      "Players": [
        "76561197999418456"
      ],
      "Score": 12
    },
    {
      "HasHat": true,
      "HatName": "MAJESTY",
      "IsCustomHat": false,
      "Players": [
        "76561197998646590"
      ],
      "Score": 9
    }
  ],
  "TimeEnded": "2019-07-27T21:51:37.4338441+02:00",
  "TimeStarted": "2019-07-27T21:51:22.3864536+02:00",
  "Winner": {
    "HasHat": true,
    "HatName": "Cyborgs",
    "IsCustomHat": false,
    "Players": [
      "76561197999418456"
    ],
    "Score": 12
  },
  "YoutubeUrl": null,
  "VideoType": 3,
  "VideoStartTime": "00:09:32.1353114",
  "VideoEndTime": "00:09:47.1827019",
  "Tags": []
}