{
  "RecordingType": 1,
  "IsCustomLevel": false,
  "LevelName": "fe6c9c0e-eb83-4588-84ff-9ecc7f46b4b5",
  "Name": "2018-04-29 22-26-56",
  "MatchName": "2018-04-29 22-16-15",
  "Players": [
    "76561197998909316",
    "76561197999418456",
    "76561197998646590"
  ],
  "Teams": [
    {
      "HasHat": true,
      "HatName": "DUCKS",
      "IsCustomHat": false,
      "Players": [
        "76561197998909316"
      ],
      "Score": 9
    },
    {
      "HasHat": true,
      "HatName": "Player 2",
      "IsCustomHat": true,
      "Players": [
        "76561197999418456"
      ],
      "Score": 9
    },
    {
      "HasHat": true,
      "HatName": "MOONWALK",
      "IsCustomHat": false,
      "Players": [
        "76561197998646590"
      ],
      "Score": 9
    }
  ],
  "TimeEnded": "2018-04-29T22:27:17.2243284+02:00",
  "TimeStarted": "2018-04-29T22:26:56.5442904+02:00",
  "Winner": {
    "HasHat": true,
    "HatName": "DUCKS",
    "IsCustomHat": false,
    "Players": [
      "76561197998909316"
    ],
    "Score": 9
  },
  "YoutubeUrl": "CAQOQxTZKSk",
  "VideoType": 2,
  "VideoMirrors": [
    {
      "MirrorType": 1,
      "URL": "https://cdn.discordapp.com/attachments/570296205272285216/572374475497275413/2018-04-29_22-26-56.mp4"
    }
  ],
  "Tags": []
}