{
  "RecordingType": 1,
  "LevelName": "2480f4d9-aa59-4f0f-9f90-1b795969df8a",
  "Name": "2019-05-08 21-40-20",
  "MatchName": "2019-05-08 21-32-57",
  "Players": [
    "76561197998646590",
    "76561197999418456",
    "76561197998909316"
  ],
  "Teams": [
    {
      "HasHat": true,
      "HatName": "DUCKS",
      "IsCustomHat": false,
      "Players": [
        "76561197998909316"
      ],
      "Score": 6
    },
    {
      "HasHat": true,
      "HatName": "Cowboys",
      "IsCustomHat": false,
      "Players": [
        "76561197999418456"
      ],
      "Score": 5
    },
    {
      "HasHat": true,
      "HatName": "MAJESTY",
      "IsCustomHat": false,
      "Players": [
        "76561197998646590"
      ],
      "Score": 12
    }
  ],
  "TimeEnded": "2019-05-08T21:40:28.7475512+02:00",
  "TimeStarted": "2019-05-08T21:40:20.7690399+02:00",
  "Winner": {
    "HasHat": true,
    "HatName": "MAJESTY",
    "IsCustomHat": false,
    "Players": [
      "76561197998646590"
    ],
    "Score": 12
  },
  "YoutubeUrl": null,
  "VideoType": 3,
  "VideoStartTime": "00:06:33.6029372",
  "VideoEndTime": "00:06:41.5814485",
  "Tags": []
}