{
  "$id": "381",
  "RecordingType": 1,
  "IsCustomLevel": true,
  "LevelName": "4e6b6554-ed23-4c94-b2f2-94214c91622a",
  "Name": "2019-06-13 22-00-21",
  "MatchName": "2019-06-13 21-55-31",
  "DatabaseIndex": "2019-06-13 22-00-21",
  "Players": [
    {
      "$id": "382",
      "DiscordId": 108174525576777728,
      "Name": "Jvs",
      "NickName": null,
      "UserId": "76561197998646590",
      "DatabaseIndex": "76561197998646590"
    },
    {
      "$id": "383",
      "DiscordId": 105698042438549504,
      "Name": "Willox",
      "NickName": null,
      "UserId": "76561197998909316",
      "DatabaseIndex": "76561197998909316"
    },
    {
      "$id": "384",
      "DiscordId": 94866365525008384,
      "Name": "MetaMan",
      "NickName": null,
      "UserId": "76561197999418456",
      "DatabaseIndex": "76561197999418456"
    }
  ],
  "Teams": [
    {
      "$id": "385",
      "HasHat": true,
      "HatName": "DUCKS",
      "IsCustomHat": false,
      "Players": [
        {
          "$id": "386",
          "DiscordId": 105698042438549504,
          "Name": "Willox",
          "NickName": null,
          "UserId": "76561197998909316",
          "DatabaseIndex": "76561197998909316"
        }
      ],
      "Score": 7
    },
    {
      "$id": "387",
      "HasHat": true,
      "HatName": "MAJESTY",
      "IsCustomHat": false,
      "Players": [
        {
          "$id": "388",
          "DiscordId": 108174525576777728,
          "Name": "Jvs",
          "NickName": null,
          "UserId": "76561197998646590",
          "DatabaseIndex": "76561197998646590"
        }
      ],
      "Score": 8
    },
    {
      "$id": "389",
      "HasHat": true,
      "HatName": "MOONWALK",
      "IsCustomHat": false,
      "Players": [
        {
          "$id": "390",
          "DiscordId": 94866365525008384,
          "Name": "MetaMan",
          "NickName": null,
          "UserId": "76561197999418456",
          "DatabaseIndex": "76561197999418456"
        }
      ],
      "Score": 3
    }
  ],
  "TimeEnded": "2019-06-13T22:00:47.6893404+02:00",
  "TimeStarted": "2019-06-13T22:00:21.8987229+02:00",
  "Winner": {
    "$ref": "385"
  },
  "YoutubeUrl": null,
  "VideoType": 2,
  "VideoMirrors": [],
  "Tags": []
}