{
  "RecordingType": 1,
  "LevelName": "3744ea0a-3261-4bde-a03b-f0c57bf4b14a",
  "Name": "2019-06-20 21-30-13",
  "MatchName": "2019-06-20 21-27-07",
  "Players": [
    "76561197998646590",
    "76561197998909316",
    "76561197999418456"
  ],
  "Teams": [
    {
      "HasHat": true,
      "HatName": "DUCKS",
      "IsCustomHat": false,
      "Players": [
        "76561197998909316"
      ],
      "Score": 4
    },
    {
      "HasHat": true,
      "HatName": "astropal",
      "IsCustomHat": false,
      "Players": [
        "76561197999418456"
      ],
      "Score": 2
    },
    {
      "HasHat": true,
      "HatName": "MAJESTY",
      "IsCustomHat": false,
      "Players": [
        "76561197998646590"
      ],
      "Score": 3
    }
  ],
  "TimeEnded": "2019-06-20T21:30:23.0154425+02:00",
  "TimeStarted": "2019-06-20T21:30:13.165566+02:00",
  "Winner": {
    "HasHat": true,
    "HatName": "DUCKS",
    "IsCustomHat": false,
    "Players": [
      "76561197998909316"
    ],
    "Score": 4
  },
  "YoutubeUrl": null,
  "VideoType": 3,
  "VideoStartTime": "00:02:51.7586712",
  "VideoEndTime": "00:03:01.6085477",
  "Tags": []
}