{
  "Name": "2018-07-08 23-15-37",
  "Players": [
    "76561197998646590",
    "76561197998909316",
    "76561197999418456"
  ],
  "Rounds": [
    "2018-07-08 23-15-38",
    "2018-07-08 23-15-51",
    "2018-07-08 23-16-06",
    "2018-07-08 23-16-19",
    "2018-07-08 23-16-37",
    "2018-07-08 23-17-12",
    "2018-07-08 23-17-32",
    "2018-07-08 23-17-46",
    "2018-07-08 23-17-58",
    "2018-07-08 23-18-09",
    "2018-07-08 23-18-27",
    "2018-07-08 23-18-41",
    "2018-07-08 23-19-00",
    "2018-07-08 23-19-14",
    "2018-07-08 23-20-09",
    "2018-07-08 23-20-21",
    "2018-07-08 23-20-42",
    "2018-07-08 23-21-02",
    "2018-07-08 23-21-20",
    "2018-07-08 23-21-40",
    "2018-07-08 23-22-04",
    "2018-07-08 23-22-41",
    "2018-07-08 23-23-04",
    "2018-07-08 23-23-49",
    "2018-07-08 23-23-59",
    "2018-07-08 23-24-14",
    "2018-07-08 23-24-28",
    "2018-07-08 23-24-49",
    "2018-07-08 23-25-04",
    "2018-07-08 23-25-22"
  ],
  "Teams": [
    {
      "HasHat": true,
      "HatName": "MOONWALK",
      "IsCustomHat": false,
      "Players": [
        "76561197998646590"
      ],
      "Score": 16
    },
    {
      "HasHat": true,
      "HatName": "DUCKS",
      "IsCustomHat": false,
      "Players": [
        "76561197998909316"
      ],
      "Score": 6
    },
    {
      "HasHat": true,
      "HatName": "Agents",
      "IsCustomHat": false,
      "Players": [
        "76561197999418456"
      ],
      "Score": 6
    }
  ],
  "TimeEnded": "2018-07-08T23:26:03.2032236+02:00",
  "TimeStarted": "2018-07-08T23:15:37.7646029+02:00",
  "Winner": {
    "HasHat": true,
    "HatName": "MOONWALK",
    "IsCustomHat": false,
    "Players": [
      "76561197998646590"
    ],
    "Score": 16
  },
  "YoutubeUrl": "PL13R2KKE1DTs_SM1tVlTVhhmd5F4IX9z_",
  "VideoType": 1,
  "VideoMirrors": [],
  "Tags": []
}