{
  "RecordingType": 1,
  "LevelName": "cd7c8c31-a4b0-453e-b8f4-ef354b9829b5",
  "Name": "2018-12-19 21-50-39",
  "MatchName": "2018-12-19 21-46-57",
  "Players": [
    "76561197998646590",
    "76561197999418456",
    "76561197998909316"
  ],
  "Teams": [
    {
      "HasHat": true,
      "HatName": "Player 2",
      "IsCustomHat": true,
      "Players": [
        "76561197999418456"
      ],
      "Score": 3
    },
    {
      "HasHat": true,
      "HatName": "DUCKS",
      "IsCustomHat": false,
      "Players": [
        "76561197998909316"
      ],
      "Score": 2
    },
    {
      "HasHat": true,
      "HatName": "MAJESTY",
      "IsCustomHat": false,
      "Players": [
        "76561197998646590"
      ],
      "Score": 5
    }
  ],
  "TimeEnded": "2018-12-19T21:50:59.6687367+01:00",
  "TimeStarted": "2018-12-19T21:50:39.6437084+01:00",
  "Winner": {
    "HasHat": true,
    "HatName": "MAJESTY",
    "IsCustomHat": false,
    "Players": [
      "76561197998646590"
    ],
    "Score": 5
  },
  "YoutubeUrl": null,
  "VideoType": 3,
  "VideoStartTime": "00:03:13.4782922",
  "VideoEndTime": "00:03:33.5033205",
  "Tags": []
}