{
  "$id": "1",
  "RecordingType": 1,
  "IsCustomLevel": false,
  "LevelName": "1f4579f4-a7ff-4f71-82c5-90157c279c5c",
  "Name": "2019-05-26 20-20-26",
  "MatchName": "2019-05-26 20-09-14",
  "Players": [
    {
      "$id": "2",
      "DiscordId": 108174525576777728,
      "Name": "Jvs",
      "NickName": null,
      "UserId": "76561197998646590"
    },
    {
      "$id": "3",
      "DiscordId": 94866365525008384,
      "Name": "MetaMan",
      "NickName": null,
      "UserId": "76561197999418456"
    },
    {
      "$id": "4",
      "DiscordId": 105698042438549504,
      "Name": "Willox",
      "NickName": null,
      "UserId": "76561197998909316"
    }
  ],
  "Teams": [
    {
      "$id": "5",
      "HasHat": true,
      "HatName": "DUCKS",
      "IsCustomHat": false,
      "Players": [
        {
          "$ref": "4"
        }
      ],
      "Score": 5
    },
    {
      "$id": "6",
      "HasHat": true,
      "HatName": "Agents",
      "IsCustomHat": false,
      "Players": [
        {
          "$ref": "3"
        }
      ],
      "Score": 12
    },
    {
      "$id": "7",
      "HasHat": true,
      "HatName": "MAJESTY",
      "IsCustomHat": false,
      "Players": [
        {
          "$ref": "2"
        }
      ],
      "Score": 15
    }
  ],
  "TimeEnded": "2019-05-26T20:20:35.6836346+02:00",
  "TimeStarted": "2019-05-26T20:20:26.7852998+02:00",
  "Winner": {
    "$ref": "6"
  },
  "YoutubeUrl": null,
  "VideoType": 2,
  "VideoMirrors": [],
  "Tags": []
}