{
  "$id": "1881",
  "RecordingType": 1,
  "IsCustomLevel": true,
  "LevelName": "0e8b0a0d-f6dd-407e-8fa0-d3a1ae58beef",
  "Name": "2019-06-17 22-06-00",
  "MatchName": "2019-06-17 22-02-56",
  "DatabaseIndex": "2019-06-17 22-06-00",
  "Players": [
    {
      "$id": "1882",
      "DiscordId": 108174525576777728,
      "Name": "Jvs",
      "NickName": null,
      "UserId": "76561197998646590",
      "DatabaseIndex": "76561197998646590"
    },
    {
      "$id": "1883",
      "DiscordId": 105698042438549504,
      "Name": "Willox",
      "NickName": null,
      "UserId": "76561197998909316",
      "DatabaseIndex": "76561197998909316"
    },
    {
      "$id": "1884",
      "DiscordId": 94866365525008384,
      "Name": "MetaMan",
      "NickName": null,
      "UserId": "76561197999418456",
      "DatabaseIndex": "76561197999418456"
    }
  ],
  "Teams": [
    {
      "$id": "1885",
      "HasHat": true,
      "HatName": "DUCKS",
      "IsCustomHat": false,
      "Players": [
        {
          "$id": "1886",
          "DiscordId": 105698042438549504,
          "Name": "Willox",
          "NickName": null,
          "UserId": "76561197998909316",
          "DatabaseIndex": "76561197998909316"
        }
      ],
      "Score": 1
    },
    {
      "$id": "1887",
      "HasHat": true,
      "HatName": "MAJESTY",
      "IsCustomHat": false,
      "Players": [
        {
          "$id": "1888",
          "DiscordId": 108174525576777728,
          "Name": "Jvs",
          "NickName": null,
          "UserId": "76561197998646590",
          "DatabaseIndex": "76561197998646590"
        }
      ],
      "Score": 4
    },
    {
      "$id": "1889",
      "HasHat": true,
      "HatName": "MOONWALK",
      "IsCustomHat": false,
      "Players": [
        {
          "$id": "1890",
          "DiscordId": 94866365525008384,
          "Name": "MetaMan",
          "NickName": null,
          "UserId": "76561197999418456",
          "DatabaseIndex": "76561197999418456"
        }
      ],
      "Score": 4
    }
  ],
  "TimeEnded": "2019-06-17T22:06:22.4188081+02:00",
  "TimeStarted": "2019-06-17T22:06:00.872775+02:00",
  "Winner": null,
  "YoutubeUrl": null,
  "VideoType": 2,
  "VideoMirrors": [],
  "Tags": []
}