{
  "RecordingType": 1,
  "LevelName": "4a7a07ed-6d0d-4e4b-94b9-4d1d7ba7d899",
  "Name": "2019-02-17 20-52-48",
  "MatchName": "2019-02-17 20-41-48",
  "Players": [
    "76561197998646590",
    "76561197998909316",
    "76561197999418456"
  ],
  "Teams": [
    {
      "HasHat": true,
      "HatName": "DUCKS",
      "IsCustomHat": false,
      "Players": [
        "76561197998909316"
      ],
      "Score": 7
    },
    {
      "HasHat": true,
      "HatName": "MAJESTY",
      "IsCustomHat": false,
      "Players": [
        "76561197998646590"
      ],
      "Score": 10
    },
    {
      "HasHat": true,
      "HatName": "MOONWALK",
      "IsCustomHat": false,
      "Players": [
        "76561197999418456"
      ],
      "Score": 15
    }
  ],
  "TimeEnded": "2019-02-17T20:52:55.3024081+01:00",
  "TimeStarted": "2019-02-17T20:52:48.3411471+01:00",
  "Winner": null,
  "YoutubeUrl": null,
  "VideoType": 3,
  "VideoStartTime": "00:09:48.9093637",
  "VideoEndTime": "00:09:55.8706247",
  "Tags": []
}