{
  "RecordingType": 1,
  "IsCustomLevel": false,
  "LevelName": "1ed096e4-6f1d-4612-bbed-ff685e671284",
  "Name": "2018-07-20 22-53-07",
  "MatchName": "2018-07-20 22-39-40",
  "Players": [
    "76561197998646590",
    "76561197998909316",
    "76561197999418456"
  ],
  "Teams": [
    {
      "HasHat": true,
      "HatName": "MAJESTY",
      "IsCustomHat": false,
      "Players": [
        "76561197998646590"
      ],
      "Score": 19
    },
    {
      "HasHat": true,
      "HatName": "DUCKS",
      "IsCustomHat": false,
      "Players": [
        "76561197998909316"
      ],
      "Score": 7
    },
    {
      "HasHat": true,
      "HatName": "Player 3",
      "IsCustomHat": true,
      "Players": [
        "76561197999418456"
      ],
      "Score": 9
    }
  ],
  "TimeEnded": "2018-07-20T22:53:30.1970905+02:00",
  "TimeStarted": "2018-07-20T22:53:07.0735399+02:00",
  "Winner": {
    "HasHat": true,
    "HatName": "Player 3",
    "IsCustomHat": true,
    "Players": [
      "76561197999418456"
    ],
    "Score": 9
  },
  "YoutubeUrl": "E7Treo6-Wng",
  "VideoType": 2,
  "VideoMirrors": [
    {
      "MirrorType": 1,
      "URL": "https://cdn.discordapp.com/attachments/570296205272285216/572688705425506314/2018-07-20_22-53-07.mp4"
    }
  ],
  "Tags": []
}