{
  "RecordingType": 1,
  "IsCustomLevel": false,
  "LevelName": "7729ab60-6cb2-431c-ad13-44d84edf799b",
  "Name": "2018-07-20 22-41-48",
  "MatchName": "2018-07-20 22-39-40",
  "Players": [
    {
      "DiscordId": 108174525576777728,
      "Name": "Jvs",
      "NickName": null,
      "UserId": "76561197998646590"
    },
    {
      "DiscordId": 105698042438549504,
      "Name": "Willox",
      "NickName": null,
      "UserId": "76561197998909316"
    },
    {
      "DiscordId": 94866365525008384,
      "Name": "metaMan",
      "NickName": null,
      "UserId": "76561197999418456"
    }
  ],
  "Teams": [
    {
      "HasHat": true,
      "HatName": "MAJESTY",
      "IsCustomHat": false,
      "Players": [
        {
          "DiscordId": 108174525576777728,
          "Name": "Jvs",
          "NickName": null,
          "UserId": "76561197998646590"
        }
      ],
      "Score": 2
    },
    {
      "HasHat": true,
      "HatName": "DUCKS",
      "IsCustomHat": false,
      "Players": [
        {
          "DiscordId": 105698042438549504,
          "Name": "Willox",
          "NickName": null,
          "UserId": "76561197998909316"
        }
      ],
      "Score": 0
    },
    {
      "HasHat": true,
      "HatName": "Player 3",
      "IsCustomHat": true,
      "Players": [
        {
          "DiscordId": 94866365525008384,
          "Name": "metaMan",
          "NickName": null,
          "UserId": "76561197999418456"
        }
      ],
      "Score": 2
    }
  ],
  "TimeEnded": "2018-07-20T22:42:05.278184+02:00",
  "TimeStarted": "2018-07-20T22:41:48.7817143+02:00",
  "Winner": {
    "HasHat": true,
    "HatName": "Player 3",
    "IsCustomHat": true,
    "Players": [
      {
        "DiscordId": 94866365525008384,
        "Name": "metaMan",
        "NickName": null,
        "UserId": "76561197999418456"
      }
    ],
    "Score": 2
  },
  "YoutubeUrl": "z5imwHVrLMU",
  "VideoType": 2,
  "VideoMirrors": [
    {
      "MirrorType": 1,
      "URL": "https://cdn.discordapp.com/attachments/570296205272285216/572688278361341952/2018-07-20_22-41-48.mp4"
    }
  ],
  "Tags": []
}