{
  "RecordingType": 1,
  "IsCustomLevel": false,
  "LevelName": "52ff2e02-eaf3-46e0-bb4a-146e17720343",
  "Name": "2018-05-12 20-48-01",
  "MatchName": "2018-05-12 20-44-11",
  "Players": [
    "76561197998909316",
    "76561197998646590",
    "76561197993900183"
  ],
  "Teams": [
    {
      "HasHat": true,
      "HatName": "DUCKS",
      "IsCustomHat": false,
      "Players": [
        "76561197998909316"
      ],
      "Score": 0
    },
    {
      "HasHat": true,
      "HatName": "MOONWALK",
      "IsCustomHat": false,
      "Players": [
        "76561197998646590"
      ],
      "Score": 1
    },
    {
      "HasHat": true,
      "HatName": "TRICORNE",
      "IsCustomHat": false,
      "Players": [
        "76561197993900183"
      ],
      "Score": 1
    }
  ],
  "TimeEnded": "2018-05-12T20:48:17.9574619+02:00",
  "TimeStarted": "2018-05-12T20:48:01.3118131+02:00",
  "Winner": null,
  "YoutubeUrl": "D9QaYB4Q4Mc",
  "VideoType": 2,
  "VideoMirrors": [
    {
      "MirrorType": 1,
      "URL": "https://cdn.discordapp.com/attachments/570296205272285216/572386858714267649/2018-05-12_20-48-01.mp4"
    }
  ],
  "Tags": []
}