{
  "RecordingType": 1,
  "IsCustomLevel": false,
  "LevelName": "d2ca9f73-9d60-4bd7-b7ac-ac524d906afc",
  "Name": "2018-11-29 21-32-54",
  "MatchName": "2018-11-29 21-22-17",
  "Players": [
    "76561197998646590",
    "76561197998909316",
    "76561197999418456"
  ],
  "Teams": [
    {
      "HasHat": true,
      "HatName": "Player 3",
      "IsCustomHat": true,
      "Players": [
        "76561197999418456"
      ],
      "Score": 7
    },
    {
      "HasHat": true,
      "HatName": "DUCKS",
      "IsCustomHat": false,
      "Players": [
        "76561197998909316"
      ],
      "Score": 8
    },
    {
      "HasHat": true,
      "HatName": "MAJESTY",
      "IsCustomHat": false,
      "Players": [
        "76561197998646590"
      ],
      "Score": 8
    }
  ],
  "TimeEnded": "2018-11-29T21:33:08.7377592+01:00",
  "TimeStarted": "2018-11-29T21:32:54.9501353+01:00",
  "Winner": null,
  "YoutubeUrl": null,
  "VideoType": 2,
  "VideoMirrors": [],
  "Tags": []
}