{
  "RecordingType": 1,
  "IsCustomLevel": false,
  "LevelName": "ce1a8ad0-a0ac-4ac7-bf2c-4e2472046d00",
  "Name": "2018-07-21 22-25-49",
  "MatchName": "2018-07-21 22-18-36",
  "Players": [
    {
      "DiscordId": 108174525576777728,
      "Name": "Jvs",
      "NickName": null,
      "UserId": "76561197998646590"
    },
    {
      "DiscordId": 105698042438549504,
      "Name": "Willox",
      "NickName": null,
      "UserId": "76561197998909316"
    },
    {
      "DiscordId": 94866365525008384,
      "Name": "metaMan",
      "NickName": null,
      "UserId": "76561197999418456"
    }
  ],
  "Teams": [
    {
      "HasHat": true,
      "HatName": "MAJESTY",
      "IsCustomHat": false,
      "Players": [
        {
          "DiscordId": 108174525576777728,
          "Name": "Jvs",
          "NickName": null,
          "UserId": "76561197998646590"
        }
      ],
      "Score": 5
    },
    {
      "HasHat": true,
      "HatName": "DUCKS",
      "IsCustomHat": false,
      "Players": [
        {
          "DiscordId": 105698042438549504,
          "Name": "Willox",
          "NickName": null,
          "UserId": "76561197998909316"
        }
      ],
      "Score": 5
    },
    {
      "HasHat": true,
      "HatName": "Player 3",
      "IsCustomHat": true,
      "Players": [
        {
          "DiscordId": 94866365525008384,
          "Name": "metaMan",
          "NickName": null,
          "UserId": "76561197999418456"
        }
      ],
      "Score": 7
    }
  ],
  "TimeEnded": "2018-07-21T22:25:58.0052669+02:00",
  "TimeStarted": "2018-07-21T22:25:49.8914298+02:00",
  "Winner": {
    "HasHat": true,
    "HatName": "Player 3",
    "IsCustomHat": true,
    "Players": [
      {
        "DiscordId": 94866365525008384,
        "Name": "metaMan",
        "NickName": null,
        "UserId": "76561197999418456"
      }
    ],
    "Score": 7
  },
  "YoutubeUrl": "jrqaRErJ8ZU",
  "VideoType": 2,
  "VideoMirrors": [
    {
      "MirrorType": 1,
      "URL": "https://cdn.discordapp.com/attachments/570296205272285216/572688978768166912/2018-07-21_22-25-49.mp4"
    }
  ],
  "Tags": []
}