{
  "RecordingType": 1,
  "IsCustomLevel": false,
  "LevelName": "2c15b996-095c-4f87-8a43-cce7f2b78074",
  "Name": "2019-02-08 21-40-21",
  "MatchName": "2019-02-08 21-28-11",
  "Players": [
    {
      "DiscordId": 108174525576777728,
      "Name": "Jvs",
      "NickName": null,
      "UserId": "76561197998646590"
    },
    {
      "DiscordId": 105698042438549504,
      "Name": "Willox",
      "NickName": null,
      "UserId": "76561197998909316"
    },
    {
      "DiscordId": 94866365525008384,
      "Name": "MetaMan",
      "NickName": null,
      "UserId": "76561197999418456"
    }
  ],
  "Teams": [
    {
      "HasHat": true,
      "HatName": "DUCKS",
      "IsCustomHat": false,
      "Players": [
        {
          "DiscordId": 105698042438549504,
          "Name": "Willox",
          "NickName": null,
          "UserId": "76561197998909316"
        }
      ],
      "Score": 12
    },
    {
      "HasHat": true,
      "HatName": "MAJESTY",
      "IsCustomHat": false,
      "Players": [
        {
          "DiscordId": 108174525576777728,
          "Name": "Jvs",
          "NickName": null,
          "UserId": "76561197998646590"
        }
      ],
      "Score": 13
    },
    {
      "HasHat": true,
      "HatName": "MOONWALK",
      "IsCustomHat": false,
      "Players": [
        {
          "DiscordId": 94866365525008384,
          "Name": "MetaMan",
          "NickName": null,
          "UserId": "76561197999418456"
        }
      ],
      "Score": 11
    }
  ],
  "TimeEnded": "2019-02-08T21:40:43.7026226+01:00",
  "TimeStarted": "2019-02-08T21:40:21.365149+01:00",
  "Winner": {
    "HasHat": true,
    "HatName": "MOONWALK",
    "IsCustomHat": false,
    "Players": [
      {
        "DiscordId": 94866365525008384,
        "Name": "MetaMan",
        "NickName": null,
        "UserId": "76561197999418456"
      }
    ],
    "Score": 11
  },
  "YoutubeUrl": null,
  "VideoType": 2,
  "VideoMirrors": [],
  "Tags": []
}