{
  "RecordingType": 1,
  "IsCustomLevel": false,
  "LevelName": "cd00ff88-b392-4fd7-ae5e-f82307f8c54d",
  "Name": "2018-06-18 22-10-40",
  "MatchName": "2018-06-18 22-02-12",
  "Players": [
    "76561197998646590",
    "76561197998909316",
    "76561197999418456"
  ],
  "Teams": [
    {
      "HasHat": true,
      "HatName": "MOONWALK",
      "IsCustomHat": false,
      "Players": [
        "76561197998646590"
      ],
      "Score": 12
    },
    {
      "HasHat": true,
      "HatName": "DUCKS",
      "IsCustomHat": false,
      "Players": [
        "76561197998909316"
      ],
      "Score": 6
    },
    {
      "HasHat": true,
      "HatName": "Player 3",
      "IsCustomHat": true,
      "Players": [
        "76561197999418456"
      ],
      "Score": 7
    }
  ],
  "TimeEnded": "2018-06-18T22:10:58.3129671+02:00",
  "TimeStarted": "2018-06-18T22:10:40.670988+02:00",
  "Winner": {
    "HasHat": true,
    "HatName": "DUCKS",
    "IsCustomHat": false,
    "Players": [
      "76561197998909316"
    ],
    "Score": 6
  },
  "YoutubeUrl": "XnI4jRl_6JY",
  "VideoType": 2,
  "VideoMirrors": [
    {
      "MirrorType": 1,
      "URL": "https://cdn.discordapp.com/attachments/570296205272285216/572472778046046209/2018-06-18_22-10-40.mp4"
    }
  ],
  "Tags": []
}