{
  "$id": "1",
  "RecordingType": 1,
  "IsCustomLevel": false,
  "LevelName": "6b0fb056-69d6-47b8-9f64-88a7f47b489b",
  "Name": "2018-09-23 21-11-19",
  "MatchName": "2018-09-23 21-11-07",
  "Players": [
    {
      "$id": "2",
      "DiscordId": 108174525576777728,
      "Name": "Jvs",
      "NickName": null,
      "UserId": "76561197998646590"
    },
    {
      "$id": "3",
      "DiscordId": 105698042438549504,
      "Name": "Willox",
      "NickName": null,
      "UserId": "76561197998909316"
    },
    {
      "$id": "4",
      "DiscordId": 150809682318065664,
      "Name": "Meepen",
      "NickName": null,
      "UserId": "76561198050165746"
    },
    {
      "$id": "5",
      "DiscordId": 94866365525008384,
      "Name": "MetaMan",
      "NickName": null,
      "UserId": "76561197999418456"
    }
  ],
  "Teams": [
    {
      "$id": "6",
      "HasHat": true,
      "HatName": "Player 4",
      "IsCustomHat": true,
      "Players": [
        {
          "$ref": "5"
        }
      ],
      "Score": 1
    },
    {
      "$id": "7",
      "HasHat": true,
      "HatName": "DUCKS",
      "IsCustomHat": false,
      "Players": [
        {
          "$ref": "3"
        }
      ],
      "Score": 1
    },
    {
      "$id": "8",
      "HasHat": true,
      "HatName": "Agents",
      "IsCustomHat": false,
      "Players": [
        {
          "$ref": "4"
        }
      ],
      "Score": 0
    },
    {
      "$id": "9",
      "HasHat": true,
      "HatName": "MAJESTY",
      "IsCustomHat": false,
      "Players": [
        {
          "$ref": "2"
        }
      ],
      "Score": 0
    }
  ],
  "TimeEnded": "2018-09-23T21:11:30.5305271+02:00",
  "TimeStarted": "2018-09-23T21:11:19.2380809+02:00",
  "Winner": {
    "$ref": "7"
  },
  "YoutubeUrl": "IqcxXjtfRbw",
  "VideoType": 2,
  "VideoMirrors": [],
  "Tags": []
}