{
  "RecordingType": 1,
  "IsCustomLevel": false,
  "LevelName": "d50ad62a-92ca-4a22-b5e7-bff0863b1d62",
  "Name": "2018-05-25 22-34-23",
  "MatchName": "2018-05-25 22-30-25",
  "Players": [
    "76561197998909316",
    "76561197998646590",
    "76561197993900183"
  ],
  "Teams": [
    {
      "HasHat": true,
      "HatName": "DUCKS",
      "IsCustomHat": false,
      "Players": [
        "76561197998909316"
      ],
      "Score": 4
    },
    {
      "HasHat": true,
      "HatName": "MOONWALK",
      "IsCustomHat": false,
      "Players": [
        "76561197998646590"
      ],
      "Score": 3
    },
    {
      "HasHat": true,
      "HatName": "Super",
      "IsCustomHat": false,
      "Players": [
        "76561197993900183"
      ],
      "Score": 3
    }
  ],
  "TimeEnded": "2018-05-25T22:34:49.8840717+02:00",
  "TimeStarted": "2018-05-25T22:34:23.4736017+02:00",
  "Winner": {
    "HasHat": true,
    "HatName": "Super",
    "IsCustomHat": false,
    "Players": [
      "76561197993900183"
    ],
    "Score": 3
  },
  "YoutubeUrl": "7mnsruQTUXI",
  "VideoType": 2,
  "VideoMirrors": [
    {
      "MirrorType": 1,
      "URL": "https://cdn.discordapp.com/attachments/570296205272285216/572457160144060417/2018-05-25_22-34-23.mp4"
    }
  ],
  "Tags": []
}